quantorch/__init__.py
quantorch/tensor.py
quantorch/calibration/__init__.py
quantorch/calibration/heston_calibration.py
quantorch/calibration/sabr_calibration.py
quantorch/calibration/vasicek_calibration.py
quantorch/core/__init__.py
quantorch/core/asset_pricing/__init__.py
quantorch/core/asset_pricing/currency_pricing.py
quantorch/core/asset_pricing/equity_forward.py
quantorch/core/asset_pricing/fixed_income_forward.py
quantorch/core/asset_pricing/futures_pricing.py
quantorch/core/asset_pricing/implied_volatility.py
quantorch/core/asset_pricing/local_volatility.py
quantorch/core/asset_pricing/bond_pricing/__init__.py
quantorch/core/asset_pricing/bond_pricing/callable_bond.py
quantorch/core/asset_pricing/bond_pricing/convertible_bond.py
quantorch/core/asset_pricing/bond_pricing/coupon_bond.py
quantorch/core/asset_pricing/bond_pricing/putable_bond.py
quantorch/core/asset_pricing/bond_pricing/stochastic_rate_bond.py
quantorch/core/asset_pricing/bond_pricing/zero_coupon_bond.py
quantorch/core/asset_pricing/option_pricing/__init__.py
quantorch/core/asset_pricing/option_pricing/advanced_exotic_options.py
quantorch/core/asset_pricing/option_pricing/american_option.py
quantorch/core/asset_pricing/option_pricing/asian_option.py
quantorch/core/asset_pricing/option_pricing/bermudan_option.py
quantorch/core/asset_pricing/option_pricing/binomial_tree.py
quantorch/core/asset_pricing/option_pricing/black_scholes_merton.py
quantorch/core/asset_pricing/option_pricing/exotic_option.py
quantorch/models/__init__.py
quantorch/models/monte_carlo.py
quantorch/models/interest_rate/__init__.py
quantorch/models/interest_rate/black_karasinski_model.py
quantorch/models/interest_rate/cir_model.py
quantorch/models/interest_rate/cirpp_model.py
quantorch/models/interest_rate/hull_white_model.py
quantorch/models/interest_rate/lmm_model.py
quantorch/models/interest_rate/vasicek_model.py
quantorch/models/local_volatility/__init__.py
quantorch/models/local_volatility/dupire_local_volatility.py
quantorch-1.0.1.dist-info/LICENSE
quantorch-1.0.1.dist-info/METADATA
quantorch-1.0.1.dist-info/WHEEL
quantorch-1.0.1.dist-info/top_level.txt
quantorch-1.0.1.dist-info/RECORD
